{
    "CLE@HOU": {"Ka'imi Fairbairn": "6 1pt PAT" , 
                "Riley Patterson":  "2 1pt PAT"
            },
    "MIA@KC": {"Harrison Butker": "2 1pt PAT", 
                "Jason Sanders": "1 1pt PAT"
            },
    "GB@DAL": {"Anders Carlson": "6 1pt PAT",
                 "Brandon Aubrey": "1 1pt PAT", 
                 "Rico Dowdle": "1 2pt PAT",
                 "Dak Prescott": "1 2pt PAT"
            },
    "LAR@DET": {"Michael Badgley": "3 1pt PAT",
                "Brett Maher": "2 1pt PAT"
            },
    "PIT@BUF": {"Tyler Bass": "4 1pt PAT",
                "Chris Boswell": "2 1pt PAT"
            },
    "PHI@TB": {"Chase McLaughlin": "3 1pt PAT"
                
            }
        
}